narada/__init__.py
narada/client.py
narada/config.py
narada/py.typed
narada/utils.py
narada/version.py
narada/window.py
narada-0.1.31.dist-info/METADATA
narada-0.1.31.dist-info/WHEEL
narada-0.1.31.dist-info/RECORD
