Metadata-Version: 2.4
Name: narada
Version: 0.1.31
Summary: Python client SDK for Narada
Project-URL: Homepage, https://github.com/NaradaAI/narada-python-sdk/narada
Project-URL: Repository, https://github.com/NaradaAI/narada-python-sdk
Project-URL: Issues, https://github.com/NaradaAI/narada-python-sdk/issues
Author-email: Narada <support@narada.ai>
License-Expression: Apache-2.0
Requires-Python: >=3.12
Requires-Dist: aiohttp>=3.12.13
Requires-Dist: narada-core==0.0.9
Requires-Dist: playwright>=1.53.0
Requires-Dist: rich>=14.0.0
Requires-Dist: semver>=3.0.4
